Workbook

Sheet Sales_Data
A1: Order_ID | B1: Order_Date | C1: Customer | D1: Product | E1: Category | F1: Region | G1: Salesperson | H1: Quantity | I1: Unit_Price | J1: Discount | K1: Payment_Mode | L1: Total sales | M1: Discount2 | N1: Value type
A2: ORD001 | B2: 46054 | C2: Meera | D2: Mouse | E2: Accessories | F2: South | G2: John | H2: 1 | I2: 800 | J2: 0.1 | K2: Cash | L2: =SalesTable[[#This Row],[Unit_Price]]*SalesTable[[#This Row],[Quantity]] -> 800 | M2: =SalesTable[[#This Row],[Total sales]]*(1-SalesTable[[#This Row],[Discount]]) -> 720 | N2: =IF(Sales_Data!M2>50000,"high value","normal value") -> normal value
A3: ORD002 | B3: 46034 | C3: Meera | D3: Webcam | E3: Accessories | F3: South | G3: Divya | H3: 1 | I3: 3500 | J3: 0 | K3: Cash | L3: =SalesTable[[#This Row],[Unit_Price]]*SalesTable[[#This Row],[Quantity]] -> 3500 | M3: =SalesTable[[#This Row],[Total sales]]*(1-SalesTable[[#This Row],[Discount]]) -> 3500 | N3: =IF(Sales_Data!M3>50000,"high value","normal value") -> normal value
A4: ORD003 | B4: 46080 | C4: Diya | D4: Monitor | E4: Electronics | F4: East | G4: John | H4: 7 | I4: 12000 | J4: 0.05 | K4: UPI | L4: =SalesTable[[#This Row],[Unit_Price]]*SalesTable[[#This Row],[Quantity]] -> 84000 | M4: =SalesTable[[#This Row],[Total sales]]*(1-SalesTable[[#This Row],[Discount]]) -> 79800 | N4: =IF(Sales_Data!M4>50000,"high value","normal value") -> high value
A5: ORD004 | B5: 46042 | C5: Meera | D5: Webcam | E5: Accessories | F5: East | G5: John | H5: 6 | I5: 3500 | J5: 0.1 | K5: Cash | L5: =SalesTable[[#This Row],[Unit_Price]]*SalesTable[[#This Row],[Quantity]] -> 21000 | M5: =SalesTable[[#This Row],[Total sales]]*(1-SalesTable[[#This Row],[Discount]]) -> 18900 | N5: =IF(Sales_Data!M5>50000,"high value","normal value") -> normal value
A6: ORD005 | B6: 46067 | C6: Diya | D6: Webcam | E6: Accessories | F6: East | G6: John | H6: 2 | I6: 3500 | J6: 0.1 | K6: Net Banking | L6: =SalesTable[[#This Row],[Unit_Price]]*SalesTable[[#This Row],[Quantity]] -> 7000 | M6: =SalesTable[[#This Row],[Total sales]]*(1-SalesTable[[#This Row],[Discount]]) -> 6300 | N6: =IF(Sales_Data!M6>50000,"high value","normal value") -> normal value
A7: ORD006 | B7: 46093 | C7: Vishnu | D7: Mouse | E7: Accessories | F7: East | G7: Divya | H7: 7 | I7: 800 | J7: 0 | K7: UPI | L7: =SalesTable[[#This Row],[Unit_Price]]*SalesTable[[#This Row],[Quantity]] -> 5600 | M7: =SalesTable[[#This Row],[Total sales]]*(1-SalesTable[[#This Row],[Discount]]) -> 5600 | N7: =IF(Sales_Data!M7>50000,"high value","normal value") -> normal value
A8: ORD007 | B8: 46060 | C8: Anjali | D8: Mouse | E8: Accessories | F8: South | G8: John | H8: 1 | I8: 800 | J8: 0.05 | K8: Net Banking | L8: =SalesTable[[#This Row],[Unit_Price]]*SalesTable[[#This Row],[Quantity]] -> 800 | M8: =SalesTable[[#This Row],[Total sales]]*(1-SalesTable[[#This Row],[Discount]]) -> 760 | N8: =IF(Sales_Data!M8>50000,"high value","normal value") -> normal value
A9: ORD008 | B9: 46043 | C9: Fathima | D9: Headset | E9: Accessories | F9: East | G9: Priya | H9: 8 | I9: 2200 | J9: 0.1 | K9: Card | L9: =SalesTable[[#This Row],[Unit_Price]]*SalesTable[[#This Row],[Quantity]] -> 17600 | M9: =SalesTable[[#This Row],[Total sales]]*(1-SalesTable[[#This Row],[Discount]]) -> 15840 | N9: =IF(Sales_Data!M9>50000,"high value","normal value") -> normal value
A10: ORD009 | B10: 46043 | C10: Sneha | D10: Mouse | E10: Accessories | F10: West | G10: Ameen | H10: 3 | I10: 800 | J10: 0.05 | K10: UPI | L10: =SalesTable[[#This Row],[Unit_Price]]*SalesTable[[#This Row],[Quantity]] -> 2400 | M10: =SalesTable[[#This Row],[Total sales]]*(1-SalesTable[[#This Row],[Discount]]) -> 2280 | N10: =IF(Sales_Data!M10>50000,"high value","normal value") -> normal value
A11: ORD010 | B11: 46027 | C11: Sanjay | D11: Printer | E11: Electronics | F11: East | G11: Kiran | H11: 1 | I11: 9500 | J11: 0.05 | K11: Card | L11: =SalesTable[[#This Row],[Unit_Price]]*SalesTable[[#This Row],[Quantity]] -> 9500 | M11: =SalesTable[[#This Row],[Total sales]]*(1-SalesTable[[#This Row],[Discount]]) -> 9025 | N11: =IF(Sales_Data!M11>50000,"high value","normal value") -> normal value
A12: ORD011 | B12: 46050 | C12: Adil | D12: Mouse | E12: Accessories | F12: West | G12: Kiran | H12: 4 | I12: 800 | J12: 0.1 | K12: Net Banking | L12: =SalesTable[[#This Row],[Unit_Price]]*SalesTable[[#This Row],[Quantity]] -> 3200 | M12: =SalesTable[[#This Row],[Total sales]]*(1-SalesTable[[#This Row],[Discount]]) -> 2880 | N12: =IF(Sales_Data!M12>50000,"high value","normal value") -> normal value
A13: ORD012 | B13: 46054 | C13: Neha | D13: Keyboard | E13: Accessories | F13: East | G13: Divya | H13: 5 | I13: 1500 | J13: 0.05 | K13: Net Banking | L13: =SalesTable[[#This Row],[Unit_Price]]*SalesTable[[#This Row],[Quantity]] -> 7500 | M13: =SalesTable[[#This Row],[Total sales]]*(1-SalesTable[[#This Row],[Discount]]) -> 7125 | N13: =IF(Sales_Data!M13>50000,"high value","normal value") -> normal value
... A51: ORD050 | B51: 46037 | C51: Riya | D51: Webcam | E51: Accessories | F51: East | G51: Priya | H51: 6 | I51: 3500 | J51: 0 | K51: Card | L51: =SalesTable[[#This Row],[Unit_Price]]*SalesTable[[#This Row],[Quantity]] -> 21000 | M51: =SalesTable[[#This Row],[Total sales]]*(1-SalesTable[[#This Row],[Discount]]) -> 21000 | N51: =IF(Sales_Data!M51>50000,"high value","normal value") -> normal value
H54: =SUM(SalesTable[Quantity]) -> 199 | I54: =AVERAGE(SalesTable[Unit_Price]) -> 8692 | K54: =COUNTIF(SalesTable[Payment_Mode],"UPI") -> 8
H55: =SUMIF(SalesTable[Region],"South",SalesTable[Quantity]) -> 28 | I55: =MAX(SalesTable[Unit_Price]) -> 55000
H56: =SUMIF(SalesTable[Category],"Electronics",SalesTable[Quantity]) -> 90 | I56: =MIN(SalesTable[Unit_Price]) -> 800
I57: =COUNTA(SalesTable[Order_ID]) -> 50

Sheet Product_Lookup
A1: Product | B1: Category | C1: Unit_Price | D1: Supplier | E1: Stock_Status
A2: Laptop | B2: Electronics | C2: 55000 | D2: TechWorld | E2: In Stock
A3: Mouse | B3: Accessories | C3: 800 | D3: Prime Systems | E3: In Stock
A4: Keyboard | B4: Accessories | C4: 1500 | D4: Smart Traders | E4: In Stock
A5: Monitor | B5: Electronics | C5: 12000 | D5: TechWorld | E5: In Stock
A6: Headset | B6: Accessories | C6: 2200 | D6: Digital Hub | E6: In Stock
A7: Printer | B7: Electronics | C7: 9500 | D7: TechWorld | E7: Low Stock
A8: Webcam | B8: Accessories | C8: 3500 | D8: Prime Systems | E8: In Stock
A9: SSD | B9: Electronics | C9: 6500 | D9: Digital Hub | E9: In Stock

Sheet 15_Tasks
A1: Task No. | B1: Excel Practical Task | C1: Suggested Function / Feature
A2: 1 | B2: Calculate the total Quantity sold for all orders. | C2: SUM
A3: 2 | B3: Calculate the average Unit Price of all products in the sales data. | C3: AVERAGE
A4: 3 | B4: Find the highest Unit Price in the sales data. | C4: MAX
A5: 4 | B5: Find the lowest Unit Price in the sales data. | C5: MIN
A6: 5 | B6: Count how many orders are present in the dataset. | C6: COUNT / COUNTA
A7: 6 | B7: Count how many orders were paid using UPI. | C7: COUNTIF
A8: 7 | B8: Calculate the total Quantity sold for the South region. | C8: SUMIF
A9: 8 | B9: Calculate the total Quantity sold for the Electronics category. | C9: SUMIF
A10: 9 | B10: Calculate the total sales value for each order using Quantity × Unit Price. | C10: Arithmetic / Formula
A11: 10 | B11: Calculate the discounted sales value for each order using Quantity × Unit Price × (1-Discount). | C11: Arithmetic / Formula
A12: 11 | B12: Using the Product_Lookup sheet, return the Category for each Product. | C12: XLOOKUP / VLOOKUP
A13: 12 | B13: Using the Product_Lookup sheet, return the Supplier for each Product. | C13: XLOOKUP / VLOOKUP
... A16: 15 | B16: Find the total discounted sales value for orders handled by salesperson 'Priya'. | C16: SUMIF / SUMIFS

Sheet Practice_Area
A1: Use this sheet to write your formulas/results.
A3: Task No. | B3: Your Formula / Result
A4: 1 | B4: =SUM(Sales_Data!H2:H51) -> 199
A5: 2 | B5: =AVERAGE(SalesTable[Unit_Price]) -> 8692
A6: 3 | B6: =MAX(Sales_Data!I2:I51) -> 55000
A7: 4 | B7: =MIN(Sales_Data!I2:I51) -> 800
A8: 5 | B8: =COUNTA(Sales_Data!A2:A51) -> 50
A9: 6 | B9: =COUNTIF(Sales_Data!K2:K51,"UPI") -> 8
A10: 7 | B10: =SUMIF(Sales_Data!F2:F51,"South",Sales_Data!H2:H51) -> 28
A11: 8 | B11: Printer | C11: =_xlfn.XLOOKUP(B11,Sales_Data!D2:D51,Sales_Data!E2:E51,"nodata",0) -> Electronics
A12: 9 | B12: Keyboard | C12: =_xlfn.XLOOKUP(B12,Product_Lookup!A2:A9,Product_Lookup!D2:D9,"no data",0) -> Smart Traders
A13: 10 | B13: Webcam | C13: =_xlfn.XLOOKUP(B13,Product_Lookup!A2:A9,Product_Lookup!E2:E9,"NO data",0) -> In Stock
A14: 11 | B14: =SUMIF(Sales_Data!G2:G51,"Priya",Sales_Data!M2:M51) -> 555530
A15: 12
A16: 13
A17: 14
A18: 15
